libcdt/__init__.py
libcdt/bin/cadet-cli
libcdt/bin/convertFile
libcdt/bin/createConvBenchmark
libcdt/bin/createLWE
libcdt/bin/createMCLin
libcdt/bin/createSCLang
libcdt/bin/createSCLin
libcdt/bin/createSCLinStep
libcdt-1.0.0.dist-info/METADATA
libcdt-1.0.0.dist-info/WHEEL
libcdt-1.0.0.dist-info/top_level.txt
libcdt-1.0.0.dist-info/RECORD
