Metadata-Version: 2.2
Name: libcdt
Version: 1.0.0
Summary: libcdt
Author: Shobhith
Classifier: Programming Language :: Python :: 3
Classifier: Operating System :: OS Independent
Dynamic: author
Dynamic: classifier
Dynamic: summary
